things_mcp/__init__.py
things_mcp/__main__.py
things_mcp/formatters.py
things_mcp/server.py
things_mcp/url_scheme.py
things_mcp-0.7.2.dist-info/METADATA
things_mcp-0.7.2.dist-info/WHEEL
things_mcp-0.7.2.dist-info/entry_points.txt
things_mcp-0.7.2.dist-info/licenses/LICENSE
things_mcp-0.7.2.dist-info/RECORD
