Metadata-Version: 2.4
Name: things-mcp
Version: 0.7.2
Summary: Things app Model Context Protocol (MCP) server
Project-URL: Homepage, https://github.com/hald/things-mcp
Project-URL: Repository, https://github.com/hald/things-mcp
Project-URL: Issues, https://github.com/hald/things-mcp/issues
License-Expression: MIT
License-File: LICENSE
Keywords: macos,mcp,model-context-protocol,task-management,things
Classifier: Development Status :: 4 - Beta
Classifier: Environment :: MacOS X
Classifier: Intended Audience :: Developers
Classifier: License :: OSI Approved :: MIT License
Classifier: Operating System :: MacOS
Classifier: Programming Language :: Python :: 3
Classifier: Programming Language :: Python :: 3.12
Classifier: Programming Language :: Python :: 3.13
Classifier: Topic :: Office/Business :: Scheduling
Requires-Python: >=3.12
Requires-Dist: fastmcp>=2.0.0
Requires-Dist: httpx>=0.28.1
Requires-Dist: things-py>=0.0.15
Provides-Extra: test
Requires-Dist: pytest-asyncio>=0.24.0; extra == 'test'
Requires-Dist: pytest-mock>=3.14.0; extra == 'test'
Requires-Dist: pytest>=8.0.0; extra == 'test'
